<Properties StartupConfiguration="WPVE.Web">
  <DisabledProjects>
    <String>WPVE/WPVE.csproj</String>
  </DisabledProjects>
  <MultiItemStartupConfigurations>
    <MultiItemSolutionRunConfiguration Id="WPVE.Web" Name="WPVE.Web">
      <Items>
        <StartupItem ItemId="{61470BE7-C8D7-4B74-A49C-FE5FDAB4CB0A}" ItemName="WPVE.Web" ConfigurationId="https" />
      </Items>
    </MultiItemSolutionRunConfiguration>
  </MultiItemStartupConfigurations>
  <MonoDevelop.Ide.DebuggingService.PinnedWatches />
  <MonoDevelop.Ide.Workspace ActiveConfiguration="Debug" />
  <MonoDevelop.Ide.ItemProperties.WPVE.Web PreferredExecutionTarget="/Applications/Safari.app" />
  <MonoDevelop.Ide.Workbench ActiveDocument="WPVE.Web/Models/HomeViewModel/HeroViewModel.cs">
    <Files>
      <File FileName="WPVE.Web/Views/Home/Index.cshtml" Line="5" Column="87" />
      <File FileName="WPVE.Web/Views/Home/_LayoutHero.cshtml" Line="1065" Column="15" />
      <File FileName="WPVE.Web/Models/HomeViewModel/HeroViewModel.cs" Line="46" Column="29" />
    </Files>
  </MonoDevelop.Ide.Workbench>
  <MonoDevelop.Ide.DebuggingService.Breakpoints>
    <BreakpointStore />
  </MonoDevelop.Ide.DebuggingService.Breakpoints>
</Properties>